{"cookies": [{"name": "gd_random", "value": "eyJtYXRjaCI6dHJ1ZSwicGVyY2VudCI6MC43ODUyNTY3MTQ0OTgxMDQzfQ==.sF9o+NGJD5HnKr5cmsGXQuT0DBolLIXKDRbS4j2wmOA=", "domain": "life.douyin.com", "path": "/p/sw.js", "expires": 1761709978.469122, "httpOnly": true, "secure": false, "sameSite": "Lax"}, {"name": "gd_random", "value": "eyJtYXRjaCI6dHJ1ZSwicGVyY2VudCI6MC43ODUyNTY3MTQ0OTgxMDQzfQ==.sF9o+NGJD5HnKr5cmsGXQuT0DBolLIXKDRbS4j2wmOA=", "domain": "life.douyin.com", "path": "/p", "expires": 1761709974.388462, "httpOnly": true, "secure": false, "sameSite": "Lax"}, {"name": "gfkadpd", "value": "299467,22075", "domain": "life.douyin.com", "path": "/", "expires": 1761364322, "httpOnly": false, "secure": true, "sameSite": "None"}, {"name": "csrf_session_id", "value": "4d7cdc604337fdc8b561bc79b86d85e6", "domain": "life.douyin.com", "path": "/", "expires": -1, "httpOnly": false, "secure": true, "sameSite": "None"}, {"name": "passport_csrf_token", "value": "1bd463aea289f04cc098598c0daa5800", "domain": ".oceanengine.com", "path": "/", "expires": 1766289123.004856, "httpOnly": false, "secure": true, "sameSite": "None"}, {"name": "ttwid", "value": "1%7Ctz9QRqo4owOINfBNSm3ipACgSmmteBx0ECPbTHbRkjc%7C1761105123%7C4d94bd93fd732dc26d7a9dbc2128eedbaf884ffe1c2ae4fffea3bdd52092cfdb", "domain": ".bytedance.com", "path": "/", "expires": 1792641123.661193, "httpOnly": true, "secure": true, "sameSite": "None"}, {"name": "sso_uid_tt_ss", "value": "57de59e06ee2f819b08326010d5a3261", "domain": ".oceanengine.com", "path": "/", "expires": 1766289170.747108, "httpOnly": true, "secure": true, "sameSite": "None"}, {"name": "toutiao_sso_user_ss", "value": "d358b5b784bc6a25ae3eb57181bfe01b", "domain": ".oceanengine.com", "path": "/", "expires": 1766289170.74714, "httpOnly": true, "secure": true, "sameSite": "None"}, {"name": "ssid_ucp_sso_v1", "value": "1.0.0-KDgzZmExZmI3ZmE0MDc5OGJkMzY2OGY2ZDNmZDIwMWFmOGQ3YWVjMTkKIAj-xLC9_cykAhCSquHHBhjRwRIgDDDF9fWjBjgBQOsHGgJsZiIgZDM1OGI1Yjc4NGJjNmEyNWFlM2ViNTcxODFiZmUwMWI", "domain": ".oceanengine.com", "path": "/", "expires": 1766289170.747158, "httpOnly": true, "secure": true, "sameSite": "None"}, {"name": "passport_csrf_token", "value": "405bc95ce431e64f394750f6b54df12b", "domain": ".douyin.com", "path": "/", "expires": 1766289170.99186, "httpOnly": false, "secure": true, "sameSite": "None"}, {"name": "passport_csrf_token_default", "value": "405bc95ce431e64f394750f6b54df12b", "domain": ".douyin.com", "path": "/", "expires": 1766289170.991912, "httpOnly": false, "secure": false, "sameSite": "Lax"}, {"name": "sid_guard_ls", "value": "2c4ec9fa8627fa9494ee21e9a5cb0320%7C1761105170%7C5184002%7CSun%2C+21-Dec-2025+03%3A52%3A52+GMT", "domain": ".life.douyin.com", "path": "/", "expires": 1792209170.991937, "httpOnly": true, "secure": true, "sameSite": "Lax"}, {"name": "sid_guard_ls", "value": "2c4ec9fa8627fa9494ee21e9a5cb0320%7C1761105170%7C5184002%7CSun%2C+21-Dec-2025+03%3A52%3A52+GMT", "domain": ".life.douyin.com", "path": "/", "expires": 1792209170.991949, "httpOnly": true, "secure": true, "sameSite": "Lax"}, {"name": "is_hit_partitioned_cookie_canary", "value": "true", "domain": ".life.douyin.com", "path": "/", "expires": 1776657170.992415, "httpOnly": true, "secure": true, "sameSite": "Lax"}, {"name": "is_hit_partitioned_cookie_canary", "value": "true", "domain": ".life.douyin.com", "path": "/", "expires": 1776657170.992429, "httpOnly": true, "secure": true, "sameSite": "Lax"}, {"name": "uid_tt_ls", "value": "de0f2839e7df982fd8e1cdc3dd677384", "domain": ".life.douyin.com", "path": "/", "expires": 1766289172.992003, "httpOnly": true, "secure": true, "sameSite": "Lax"}, {"name": "uid_tt_ls", "value": "de0f2839e7df982fd8e1cdc3dd677384", "domain": ".life.douyin.com", "path": "/", "expires": 1766289172.992014, "httpOnly": true, "secure": true, "sameSite": "Lax"}, {"name": "uid_tt_ss_ls", "value": "de0f2839e7df982fd8e1cdc3dd677384", "domain": ".life.douyin.com", "path": "/", "expires": 1766289172.992057, "httpOnly": true, "secure": true, "sameSite": "None"}, {"name": "uid_tt_ss_ls", "value": "de0f2839e7df982fd8e1cdc3dd677384", "domain": ".life.douyin.com", "path": "/", "expires": 1766289172.992068, "httpOnly": true, "secure": true, "sameSite": "None"}, {"name": "is_hit_partitioned_cookie_canary_ss", "value": "true", "domain": ".life.douyin.com", "path": "/", "expires": 1776657170.99247, "httpOnly": true, "secure": true, "sameSite": "None"}, {"name": "is_hit_partitioned_cookie_canary_ss", "value": "true", "domain": ".life.douyin.com", "path": "/", "expires": 1776657170.992484, "httpOnly": true, "secure": true, "sameSite": "None"}, {"name": "sid_tt_ls", "value": "2c4ec9fa8627fa9494ee21e9a5cb0320", "domain": ".life.douyin.com", "path": "/", "expires": 1766289172.992118, "httpOnly": true, "secure": true, "sameSite": "Lax"}, {"name": "sid_tt_ls", "value": "2c4ec9fa8627fa9494ee21e9a5cb0320", "domain": ".life.douyin.com", "path": "/", "expires": 1766289172.99213, "httpOnly": true, "secure": true, "sameSite": "Lax"}, {"name": "sessionid_ls", "value": "2c4ec9fa8627fa9494ee21e9a5cb0320", "domain": ".life.douyin.com", "path": "/", "expires": 1766289172.992173, "httpOnly": true, "secure": true, "sameSite": "Lax"}, {"name": "sessionid_ls", "value": "2c4ec9fa8627fa9494ee21e9a5cb0320", "domain": ".life.douyin.com", "path": "/", "expires": 1766289172.992183, "httpOnly": true, "secure": true, "sameSite": "Lax"}, {"name": "sessionid_ss_ls", "value": "2c4ec9fa8627fa9494ee21e9a5cb0320", "domain": ".life.douyin.com", "path": "/", "expires": 1766289172.992225, "httpOnly": true, "secure": true, "sameSite": "None"}, {"name": "sessionid_ss_ls", "value": "2c4ec9fa8627fa9494ee21e9a5cb0320", "domain": ".life.douyin.com", "path": "/", "expires": 1766289172.992235, "httpOnly": true, "secure": true, "sameSite": "None"}, {"name": "session_tlb_tag_ls", "value": "sttt%7C2%7CLE7J-oYn-pSU7iHppcsDIP_________44E3Kf28XFodY5s2VJU4z6EXiTRlX7mooLREyoF9uQnc%3D", "domain": ".life.douyin.com", "path": "/", "expires": 1766289172.992278, "httpOnly": true, "secure": true, "sameSite": "None"}, {"name": "session_tlb_tag_ls", "value": "sttt%7C2%7CLE7J-oYn-pSU7iHppcsDIP_________44E3Kf28XFodY5s2VJU4z6EXiTRlX7mooLREyoF9uQnc%3D", "domain": ".life.douyin.com", "path": "/", "expires": 1766289172.992289, "httpOnly": true, "secure": true, "sameSite": "None"}, {"name": "is_staff_user_ls", "value": "false", "domain": ".life.douyin.com", "path": "/", "expires": 1766289172.992331, "httpOnly": true, "secure": true, "sameSite": "Lax"}, {"name": "is_staff_user_ls", "value": "false", "domain": ".life.douyin.com", "path": "/", "expires": 1766289172.99234, "httpOnly": true, "secure": true, "sameSite": "Lax"}, {"name": "sid_ucp_v1_ls", "value": "1.0.0-KGFkZmU0NzgxYjQ1MmM1MDQwZDg1ODRkNGNhMTYzOWZmMmQxMjI3NGUKGgj-xLC9_cykAhCSquHHBhjRwRIgDDgBQOsHGgJobCIgMmM0ZWM5ZmE4NjI3ZmE5NDk0ZWUyMWU5YTVjYjAzMjA", "domain": ".life.douyin.com", "path": "/", "expires": 1766289172.992391, "httpOnly": true, "secure": true, "sameSite": "Lax"}, {"name": "sid_ucp_v1_ls", "value": "1.0.0-KGFkZmU0NzgxYjQ1MmM1MDQwZDg1ODRkNGNhMTYzOWZmMmQxMjI3NGUKGgj-xLC9_cykAhCSquHHBhjRwRIgDDgBQOsHGgJobCIgMmM0ZWM5ZmE4NjI3ZmE5NDk0ZWUyMWU5YTVjYjAzMjA", "domain": ".life.douyin.com", "path": "/", "expires": 1766289172.992402, "httpOnly": true, "secure": true, "sameSite": "Lax"}, {"name": "ssid_ucp_v1_ls", "value": "1.0.0-KGFkZmU0NzgxYjQ1MmM1MDQwZDg1ODRkNGNhMTYzOWZmMmQxMjI3NGUKGgj-xLC9_cykAhCSquHHBhjRwRIgDDgBQOsHGgJobCIgMmM0ZWM5ZmE4NjI3ZmE5NDk0ZWUyMWU5YTVjYjAzMjA", "domain": ".life.douyin.com", "path": "/", "expires": 1766289172.992446, "httpOnly": true, "secure": true, "sameSite": "None"}, {"name": "ssid_ucp_v1_ls", "value": "1.0.0-KGFkZmU0NzgxYjQ1MmM1MDQwZDg1ODRkNGNhMTYzOWZmMmQxMjI3NGUKGgj-xLC9_cykAhCSquHHBhjRwRIgDDgBQOsHGgJobCIgMmM0ZWM5ZmE4NjI3ZmE5NDk0ZWUyMWU5YTVjYjAzMjA", "domain": ".life.douyin.com", "path": "/", "expires": 1766289172.992457, "httpOnly": true, "secure": true, "sameSite": "None"}, {"name": "odin_tt", "value": "98f6b533ba898d023892150fd73687069854c66f0276be866dce4ce6773b3cd4b2eb58a8be954de61adcf6e32c1cf5bb", "domain": ".douyin.com", "path": "/", "expires": 1792641171.663474, "httpOnly": true, "secure": false, "sameSite": "Lax"}, {"name": "ttwid", "value": "1%7Ctz9QRqo4owOINfBNSm3ipACgSmmteBx0ECPbTHbRkjc%7C1761105174%7Cf99feaa3b46a8574a1f2edde2e4f9979fcb1e276a572d8c449e7d4009a0d83ed", "domain": ".oceanengine.com", "path": "/", "expires": 1792641174.571427, "httpOnly": true, "secure": true, "sameSite": "None"}, {"name": "ttwid", "value": "1%7Ctz9QRqo4owOINfBNSm3ipACgSmmteBx0ECPbTHbRkjc%7C1761105174%7Cf99feaa3b46a8574a1f2edde2e4f9979fcb1e276a572d8c449e7d4009a0d83ed", "domain": ".douyin.com", "path": "/", "expires": 1792641174.644891, "httpOnly": true, "secure": true, "sameSite": "None"}, {"name": "fg_uid", "value": "RID20251022115255BBADFC3822C9A5159DE5", "domain": "api.feelgood.cn", "path": "/", "expires": 1792641175.885536, "httpOnly": false, "secure": true, "sameSite": "None"}], "origins": [{"origin": "https://life.douyin.com", "localStorage": [{"name": "__tea_cache_tokens_307119", "value": "{\"web_id\":\"7563888874510927387\",\"user_unique_id\":\"7563888874510927387\",\"timestamp\":1761105174499,\"_type_\":\"default\"}"}, {"name": "SLARDARfulfillment_verify_pc", "value": "JTdCJTIydXNlcklkJTIyOiUyMjEyODY4NzQ2MDQ1MTE4NzAlMjIsJTIyZGV2aWNlSWQlMjI6JTIyYjU0MmU1MmEtMjY5Mi00MTZjLTlhNjItMWM0YjYyYjBkYjE2JTIyLCUyMmV4cGlyZXMlMjI6MTc2ODg4MTE3NTUwNiU3RA=="}, {"name": "__tea_cache_tokens_303313", "value": "{\"web_id\":\"7563888872528168458\",\"user_unique_id\":\"1286874604511870\",\"timestamp\":1761105174851,\"_type_\":\"default\"}"}, {"name": "__msuuid__", "value": "6ebc5573-c10b-4be3-b00f-a5555318f0f4"}, {"name": "SLARDARfe_ls_merchant_react_pc_core", "value": "JTdCJTIydXNlcklkJTIyOiUyMjUyMjU2NTViLWYyZDItNDhhMy05MjM2LTYyZjE2MmZkNTNlMyUyMiwlMjJkZXZpY2VJZCUyMjolMjJjZGE0ODE3NC0xYWU2LTQ0OWEtOTQ4ZC01ZDY0OWY3ZDUwMzElMjIsJTIyZXhwaXJlcyUyMjoxNzY4ODgxMTc0NTIxJTdE"}, {"name": "__tea_cache_first_307119", "value": "1"}, {"name": "xmst", "value": "UyA4teEBBqCFDAAkZDKDh2Va2DDNJ5xVgcVb1Q2SJcQRuUdvWQ8M_jG_UTUbXpzsDbr08TbZw_o3pSwaU8Yq1zyF0CqRBXUXvqXEUBmHK97vHosUvI5beaJ2d7ujOpLu__Z_1kGRgCwETLMvQ10JqOwqHsmkGtCcWsokYh0aRZI="}, {"name": "root_life_account_id", "value": "{\"1286874604511870\":\"7241078611527075855\"}"}, {"name": "1286874604511870_bd_tooltip", "value": "1"}, {"name": "__tea_cache_first_303313", "value": "1"}, {"name": "experiment_config", "value": "{\"group\":\"adv_sw_single\",\"garfishEnabled\":false,\"swEnabled\":true,\"parallelLimit\":1}"}, {"name": "SLARDARleads_cs_life", "value": "JTdCJTIydXNlcklkJTIyOiUyMjIwMzBkNmE1LWUyOWEtNGU3MC1hNmI1LTY0MjYxNTA5NjNkYyUyMiwlMjJkZXZpY2VJZCUyMjolMjJmODI5MmMwNi03YzVmLTQ2NjQtOTU1Mi1mYTA4MjFjNTZmZmMlMjIsJTIyZXhwaXJlcyUyMjoxNzY4ODgxMTc2NDk4JTdE"}, {"name": "__tea_cache_tokens_583766", "value": "{\"web_id\":\"7563889102974928422\",\"user_unique_id\":\"7563889102974928422\",\"timestamp\":1761105176430,\"_type_\":\"default\"}"}, {"name": "SLARDARuc_secure_sdk", "value": "JTdCJTIydXNlcklkJTIyOiUyMmMzMDdlYzlmLTE1ZDktNGIyMy04ODFmLWU5MTgyNmE5ZjNhOCUyMiwlMjJkZXZpY2VJZCUyMjolMjI1OWU0YmQ5Yy1iMjhjLTQ1NmQtODEzZi0yMDUxM2E1ZWU3OWIlMjIsJTIyZXhwaXJlcyUyMjoxNzY4ODgxMTc2NDk2JTdE"}, {"name": "__tea_sdk_ab_version_303313", "value": "{\"data\":{\"ls_home_total_fmp_opt_v1\":{\"val\":{\"async_create_status_view\":true,\"async_preload_template\":true,\"delay_attach_assistant\":true,\"delay_attach_my_page\":true,\"delay_jsb_registry\":true,\"enable_jato\":true,\"preload_home_place_holder\":true},\"vid\":\"90167856\"},\"ls_praise_dialog_setting\":{\"val\":{\"app_market_order\":\"com.oppo.market|com.heytap.market|com.tencent.android.qqdownloader|com.qihoo.appstore|com.wandoujia.phoenix2|com.baidu.appsearch|com.sogou.androidtool|com.huawei.appmarket|com.bbk.appstore|com.xiaomi.market|com.meizu.mstore|com.sec.android.app.samsungapps|com.yingyonghui.market|com.hiapk.marketpho\",\"guide_style_1_market_list\":\"com.oppo.market|com.tencent.android.qqdownloader|com.meizu.mstore|com.qihoo.appstore|com.baidu.appsearch|com.sogou.androidtool|com.huawei.appmarket|com.wandoujia.phoenix2\",\"guide_style_2_market_list\":\"com.oppo.market\",\"market_feedback_dialog_enable\":\"0\",\"market_feedback_url\":\"aweme://webview?url=https://survey.feelgood.cn/s/?taskID=7441484093121888293\"},\"vid\":\"90608956\"},\"miniapp_login_type\":{\"val\":3,\"vid\":\"13896368\"},\"pia_global_config\":{\"val\":{\"allow_domains\":[\"jinritemai.com\",\"bytegecko.com\",\"snssdk.com\",\"ecombdstatic.com\",\"bytefae.com\",\"amemv.com\",\"baohuaxia.com\",\"bytescm.com\",\"bytedance.net\",\"baike.com\",\"pay.fund.yilucaifu.com\",\"leads.oceanengine.com\",\"life.douyin.com\",\"localads.chengzijianzhan.cn\"],\"blocked_pages\":[],\"blocked_pages_v1\":[],\"boot\":true,\"cache\":true,\"experiment_disable_pia_query\":true,\"features\":[\"cache\",\"nsr\",\"prefetch\",\"snapshot\",\"streaming\"],\"html_intercept_timeout\":20,\"js_engine\":\"quick\",\"main\":true,\"multi_thread_worker\":false,\"nsr_v1\":false,\"prefetch_v1\":false,\"snapshot_v1\":false,\"url_rules\":[\"^life.^douyin.^com/^h5/^alliance/^merchant_app/*\",\"^life.^douyin.^com/^h5/^alliance/^merchant_app/*/*\",\"^life.^douyin.^com/^h5/^alliance/^merchant_app/*/*/*\"],\"vanilla_fetch\":true,\"warmup\":true,\"worker\":true},\"vid\":\"90127146\"},\"pia_page/life-douyin-com/h5/marketing/activity/list\":{\"val\":{\"_pia_\":1,\"features\":[\"prefetch\"]},\"vid\":\"91095814\"},\"pia_page/life-douyin-com/h5/marketing/apply/investment/select--deploy--unify\":{\"val\":{\"_pia_\":1,\"features\":[\"prefetch\"]},\"vid\":\"91276235\"},\"pia_page/life-douyin-com/h5/marketing/apply/investment/super--coupon/select--deploy--unify\":{\"val\":{\"_pia_\":1,\"features\":[\"prefetch\"]},\"vid\":\"91276234\"}},\"uuid\":\"1286874604511870\",\"timestamp\":1761105174585,\"ab_version_multilink\":[],\"ab_ext_version\":[],\"ab_version\":[]}"}, {"name": "=^_^=athena_web_id", "value": "4ecf52f0-04fe-4617-b113-aa5a3f141fe5"}, {"name": "SERVICE_SCORE_GUIDE_KEY_7241078611527075855_1286874604511870", "value": "true"}, {"name": "SLARDARgoofy_deploy_micro_fe_sdk", "value": "JTdCJTIydXNlcklkJTIyOiUyMjg4NWY3MjRlLTQwNWYtNDlmMC1hZTkxLTExMDkzZmE5ZGQ2NiUyMiwlMjJkZXZpY2VJZCUyMjolMjIwYTg0ZWI2YS05NDA2LTQzNDYtOTc2ZS0yNzQ3OTRhMDIzNGIlMjIsJTIyZXhwaXJlcyUyMjoxNzY4ODgxMTc0NTIwJTdE"}, {"name": "SLARDARpoi_select", "value": "JTdCJTIydXNlcklkJTIyOiUyMjEyODY4NzQ2MDQ1MTE4NzAlMjIsJTIyZGV2aWNlSWQlMjI6JTIyOWI4MWU0NWItYmFiOS00YTQ2LWE3ODktMzI4ZTJkZTE5OTVlJTIyLCUyMmV4cGlyZXMlMjI6MTc2ODg4MTE3NTI0OSU3RA=="}, {"name": "SLARDARfe_ls_merchant_react_pc_browser_update", "value": "{\"userId\":\"d95aaaad-1aa1-a92f-7f60-3f5db73b4057\",\"deviceId\":\"2ded6763-906d-4242-a98d-79d5b9053c4b\"}"}, {"name": "__tea_cache_first_583766", "value": "1"}, {"name": "CORE_BIZ_VIEW_TYPE_CACHE", "value": "{\"7241078611527075855-1286874604511870\":\"1\"}"}, {"name": "SLARDARlife_mkt_merchant_module", "value": "JTdCJTIydXNlcklkJTIyOiUyMjEyODY4NzQ2MDQ1MTE4NzAlMjIsJTIyZGV2aWNlSWQlMjI6JTIyMTQxNWMwNWItNmY4MS00ZmYxLWEwZDItNzE5YTEzZDc1M2UyJTIyLCUyMmV4cGlyZXMlMjI6MTc2ODg4MTE3NjU2MiU3RA=="}, {"name": "exp_track_config", "value": "{\"time\":1761105122877,\"config\":[{\"_id\":\"62961a4705151b0048334f07\",\"business_type\":\"\u670d\u52a1\u5546\u5165\u9a7b - \u57fa\u7840\u4fe1\u606f\u8868\u5355\u586b\u5199\",\"survey\":[],\"createdAt\":\"2022-05-31T13:38:15.341Z\",\"updatedAt\":\"2022-07-14T02:27:45.164Z\"},{\"_id\":\"62a73f477a124ed366dcbc18\",\"business_type\":\"ls_merchant_pc_bd_plan\",\"replay\":[],\"createdAt\":\"2022-06-13T13:44:39.368Z\",\"updatedAt\":\"2022-11-03T12:11:31.867Z\"},{\"_id\":\"62a73f857a124ed366dcbc6b\",\"business_type\":\"start_customer_private_transfer\",\"survey\":[{\"configName\":\"\u8868\u5355\u5b8c\u6210\",\"survey\":\"\u89e6\u53d1exp\u65f6\u5c55\u73b0__exp\"}],\"createdAt\":\"2022-06-13T13:45:41.601Z\",\"updatedAt\":\"2022-07-14T02:27:45.185Z\"},{\"_id\":\"62a740ce7a124ed366dcbc91\",\"business_type\":\"start_clue_public_transfer\",\"survey\":[{\"configName\":\"\u8868\u5355\u5b8c\u6210\",\"survey\":\"\u89e6\u53d1exp\u65f6\u5c55\u73b0__exp\"}],\"createdAt\":\"2022-06-13T13:51:10.619Z\",\"updatedAt\":\"2022-07-14T02:27:45.194Z\"},{\"_id\":\"62a7ece77a124ed366dcbd63\",\"business_type\":\"web_certification\",\"replay\":[],\"createdAt\":\"2022-06-14T02:05:27.445Z\",\"updatedAt\":\"2022-07-14T02:27:45.204Z\"}]}"}, {"name": "exp_track_cur_flow_start", "value": "{\"curFlow\":\"ls_merchant_pc_login\",\"startTime\":1761105172338,\"isSurveyTrigger\":false}"}]}]}
